README.rst
setup.py
hnr_downloader/__init__.py
hnr_downloader/add.py
hnr_downloader/config.json
hnr_downloader/config.py
hnr_downloader/downloader.py
hnr_downloader/helper.py
hnr_downloader/log.json
hnr_downloader/main.py
hnr_downloader.egg-info/PKG-INFO
hnr_downloader.egg-info/SOURCES.txt
hnr_downloader.egg-info/dependency_links.txt
hnr_downloader.egg-info/entry_points.txt
hnr_downloader.egg-info/requires.txt
hnr_downloader.egg-info/top_level.txt
hnr_downloader/i18n/__init__.py
hnr_downloader/i18n/i18n.py
hnr_downloader/i18n/lang.json
hnr_downloader/i18n/locale/en/LC_MESSAGES/hnr.mo
hnr_downloader/i18n/locale/en/LC_MESSAGES/hnr.po
hnr_downloader/i18n/locale/zh_CN/LC_MESSAGES/hnr.mo
hnr_downloader/i18n/locale/zh_CN/LC_MESSAGES/hnr.po
hnr_downloader/i18n/locale/zh_TW/LC_MESSAGES/hnr.mo
hnr_downloader/i18n/locale/zh_TW/LC_MESSAGES/hnr.po
hnr_downloader/scripts/__init__.py
hnr_downloader/scripts/copytext.py
hnr_downloader/scripts/msgfmt.py
hnr_downloader/scripts/pygettext.py