Metadata-Version: 1.2
Name: hnr-downloader
Version: 1.0.0.1
Summary: A download manager by Python.
Home-page: https://github.com/dergenlee/hnr_downloader
Author: Dergen Lee
Author-email: dergenlee@163.com
License: UNKNOWN
Project-URL: Documentation, https://github.com/dergenlee/hnr_downloader
Project-URL: Funding, https://donate.pypi.org
Project-URL: Source, https://github.com/dergenlee/hnr_downloader
Project-URL: Tracker, https://github.com/dergenlee/hnr_downloader/issues
Keywords: download manager
Platform: UNKNOWN
Classifier: Development Status :: 5 - Production/Stable
Classifier: Intended Audience :: Developers
Classifier: Intended Audience :: End Users/Desktop
Classifier: Topic :: Utilities
Classifier: License :: OSI Approved :: Apache Software License
Classifier: Programming Language :: Python :: 3
Classifier: Programming Language :: Python :: 3.6
Classifier: Programming Language :: Python :: 3.7
Classifier: Programming Language :: Python :: 3.8
Requires-Python: >=3
